LICENSE
MANIFEST.in
README.md
requirements.txt
setup.py
bin/build-relational-database.py
veba_core/__init__.py
veba_core/relational.py
veba_core.egg-info/PKG-INFO
veba_core.egg-info/SOURCES.txt
veba_core.egg-info/dependency_links.txt
veba_core.egg-info/requires.txt
veba_core.egg-info/top_level.txt