Metadata-Version: 2.4
Name: veba_core
Version: 2025.5.2
Summary: Core utilities for VEBA
Home-page: https://github.com/jolespin/veba_core
Author: Josh L. Espinoza
Author-email: jol.espinoz@gmail.com
License: GNU AGPL_v3 License
License-File: LICENSE
Requires-Dist: pathlib
Requires-Dist: tqdm
Requires-Dist: memory_profiler
Requires-Dist: pandas
Requires-Dist: sqlalchemy
Requires-Dist: pyfastx
Requires-Dist: pyexeggutor>=2024.11.18
Dynamic: author
Dynamic: author-email
Dynamic: home-page
Dynamic: license
Dynamic: license-file
Dynamic: requires-dist
Dynamic: summary
